yiyangzhang0201/__init__.py
yiyangzhang0201/fileop.py
yiyangzhang0201/regcov.py
yiyangzhang0201-0.1.7.dist-info/METADATA
yiyangzhang0201-0.1.7.dist-info/WHEEL
yiyangzhang0201-0.1.7.dist-info/top_level.txt
yiyangzhang0201-0.1.7.dist-info/RECORD
