Metadata-Version: 2.1
Name: yiyangzhang0201
Version: 0.1.7
Summary: A Personal Package for Academic Use
Author: Yiyang Zhang
Author-email: zhangyy237@gmail.com
Classifier: Programming Language :: Python :: 3
Classifier: License :: OSI Approved :: MIT License
Classifier: Operating System :: OS Independent
Requires-Python: >=3.8
